[
        {
            "fecha_hora": "2018-01-17 00:00:00",
            "chancador": "PRIM DOS",
            "viajes": "7",
            "tons": "2086",
            "tons_promedio": "298",
            "tiempo_cola": "0.552380952",
            "Distancia": "1.344428571",
            "velocidad": "16.3827853",
            "ley": "0.59",
            "SPI": "106.4"
        },
        {
            "fecha_hora": "2018-01-17 01:00:00",
            "chancador": "PRIM DOS",
            "viajes": "5",
            "tons": "1490",
            "tons_promedio": "298",
            "tiempo_cola": "2.496666667",
            "Distancia": "1.1692",
            "velocidad": "12.40164997",
            "ley": "0.59",
            "SPI": "106.4"
        },
        {
            "fecha_hora": "2018-01-17 02:00:00",
            "chancador": "PRIM DOS",
            "viajes": "5",
            "tons": "1490",
            "tons_promedio": "298",
            "tiempo_cola": "1.233333333",
            "Distancia": "3.8542",
            "velocidad": "30.87476636",
            "ley": "0.59",
            "SPI": "106.4"
        },
        {
            "fecha_hora": "2018-01-17 03:00:00",
            "chancador": "PRIM DOS",
            "viajes": "9",
            "tons": "2709",
            "tons_promedio": "301",
            "tiempo_cola": "1.077777778",
            "Distancia": "2.658611111",
            "velocidad": "16.152072",
            "ley": "0.675799188",
            "SPI": "119.815873"
        },
        {
            "fecha_hora": "2018-01-17 04:00:00",
            "chancador": "PRIM DOS",
            "viajes": "15",
            "tons": "4497",
            "tons_promedio": "299.8",
            "tiempo_cola": "4.092222222",
            "Distancia": "2.593466667",
            "velocidad": "19.2359316",
            "ley": "0.670182344",
            "SPI": "118.9376028"
        },
        {
            "fecha_hora": "2018-01-17 05:00:00",
            "chancador": "PRIM",
            "viajes": "5",
            "tons": "1490",
            "tons_promedio": "298",
            "tiempo_cola": "1.646666667",
            "Distancia": "9.4725",
            "velocidad": "18.271003",
            "ley": "0.62",
            "SPI": "142"
        },
        {
            "fecha_hora": "2018-01-17 05:00:00",
            "chancador": "PRIM DOS",
            "viajes": "13",
            "tons": "3874",
            "tons_promedio": "298",
            "tiempo_cola": "1.784615385",
            "Distancia": "1.792192308",
            "velocidad": "19.4830662",
            "ley": "0.691538462",
            "SPI": "122.2769231"
        },
        {
            "fecha_hora": "2018-01-17 06:00:00",
            "chancador": "PRIM DOS",
            "viajes": "13",
            "tons": "3928",
            "tons_promedio": "302.1538462",
            "tiempo_cola": "0.782051282",
            "Distancia": "1.936615385",
            "velocidad": "18.4514658",
            "ley": "0.677240326",
            "SPI": "122.3861507"
        },
        {
            "fecha_hora": "2018-01-17 07:00:00",
            "chancador": "PRIM DOS",
            "viajes": "12",
            "tons": "3630",
            "tons_promedio": "302.5",
            "tiempo_cola": "0.841666667",
            "Distancia": "1.29375",
            "velocidad": "13.44964505",
            "ley": "0.654848485",
            "SPI": "116.5399449"
        },
        {
            "fecha_hora": "2018-01-17 08:00:00",
            "chancador": "PRIM DOS",
            "viajes": "20",
            "tons": "6014",
            "tons_promedio": "300.7",
            "tiempo_cola": "1.145",
            "Distancia": "8.292875",
            "velocidad": "36.03856832",
            "ley": "0.612567343",
            "SPI": "133.1799135"
        },
        {
            "fecha_hora": "2018-01-17 09:00:00",
            "chancador": "PRIM DOS",
            "viajes": "15",
            "tons": "4551",
            "tons_promedio": "303.4",
            "tiempo_cola": "1.033333333",
            "Distancia": "8.3669",
            "velocidad": "19.40942521",
            "ley": "0.62",
            "SPI": "142"
        },
        {
            "fecha_hora": "2018-01-17 10:00:00",
            "chancador": "PRIM DOS",
            "viajes": "18",
            "tons": "5445",
            "tons_promedio": "302.5",
            "tiempo_cola": "1.774074074",
            "Distancia": "8.633388889",
            "velocidad": "20.97376047",
            "ley": "0.618358127",
            "SPI": "140.0516437"
        },
        {
            "fecha_hora": "2018-01-17 11:00:00",
            "chancador": "PRIM DOS",
            "viajes": "16",
            "tons": "4849",
            "tons_promedio": "303.0625",
            "tiempo_cola": "2.623958333",
            "Distancia": "8.85446875",
            "velocidad": "18.49530924",
            "ley": "0.642066405",
            "SPI": "159.0793978"
        },
        {
            "fecha_hora": "2018-01-17 12:00:00",
            "chancador": "PRIM",
            "viajes": "8",
            "tons": "2438",
            "tons_promedio": "304.75",
            "tiempo_cola": "0.55625",
            "Distancia": "9.8925625",
            "velocidad": "23.36442513",
            "ley": "0.67",
            "SPI": "180.7"
        },
        {
            "fecha_hora": "2018-01-17 12:00:00",
            "chancador": "PRIM DOS",
            "viajes": "10",
            "tons": "3061",
            "tons_promedio": "306.1",
            "tiempo_cola": "3.928333333",
            "Distancia": "9.66795",
            "velocidad": "22.16431255",
            "ley": "0.67",
            "SPI": "180.7"
        },
        {
            "fecha_hora": "2018-01-17 13:00:00",
            "chancador": "PRIM",
            "viajes": "11",
            "tons": "3332",
            "tons_promedio": "302.9090909",
            "tiempo_cola": "0.121212121",
            "Distancia": "10.42163636",
            "velocidad": "22.17071638",
            "ley": "0.67",
            "SPI": "180.7"
        },
        {
            "fecha_hora": "2018-01-17 13:00:00",
            "chancador": "PRIM DOS",
            "viajes": "8",
            "tons": "2384",
            "tons_promedio": "298",
            "tiempo_cola": "0.841666667",
            "Distancia": "7.3775",
            "velocidad": "20.02941176",
            "ley": "0.625",
            "SPI": "156.69625"
        },
        {
            "fecha_hora": "2018-01-17 14:00:00",
            "chancador": "PRIM",
            "viajes": "2",
            "tons": "623",
            "tons_promedio": "311.5",
            "tiempo_cola": "0.308333333",
            "Distancia": "10.7755",
            "velocidad": "22.65876168",
            "ley": "0.67",
            "SPI": "180.7"
        },
        {
            "fecha_hora": "2018-01-17 14:00:00",
            "chancador": "PRIM DOS",
            "viajes": "5",
            "tons": "1490",
            "tons_promedio": "298",
            "tiempo_cola": "2.983333333",
            "Distancia": "2.8481",
            "velocidad": "17.14575251",
            "ley": "0.55",
            "SPI": "116.69"
        },
        {
            "fecha_hora": "2018-01-17 15:00:00",
            "chancador": "PRIM",
            "viajes": "7",
            "tons": "2113",
            "tons_promedio": "301.8571429",
            "tiempo_cola": "0.126190476",
            "Distancia": "8.201714286",
            "velocidad": "19.95493121",
            "ley": "0.67",
            "SPI": "180.7"
        },
        {
            "fecha_hora": "2018-01-17 15:00:00",
            "chancador": "PRIM DOS",
            "viajes": "7",
            "tons": "2086",
            "tons_promedio": "298",
            "tiempo_cola": "2.776190476",
            "Distancia": "2.499357143",
            "velocidad": "18.67570052",
            "ley": "0.567142857",
            "SPI": "125.8342857"
        },
        {
            "fecha_hora": "2018-01-17 16:00:00",
            "chancador": "PRIM DOS",
            "viajes": "5",
            "tons": "1490",
            "tons_promedio": "298",
            "tiempo_cola": "0.75",
            "Distancia": "1.8417",
            "velocidad": "11.56281828",
            "ley": "0.55",
            "SPI": "116.69"
        },
        {
            "fecha_hora": "2018-01-17 17:00:00",
            "chancador": "PRIM DOS",
            "viajes": "10",
            "tons": "3007",
            "tons_promedio": "300.7",
            "tiempo_cola": "0.513333333",
            "Distancia": "5.3906",
            "velocidad": "17.45393713",
            "ley": "0.622430994",
            "SPI": "155.3258996"
        },
        {
            "fecha_hora": "2018-01-17 18:00:00",
            "chancador": "PRIM",
            "viajes": "11",
            "tons": "3413",
            "tons_promedio": "310.2727273",
            "tiempo_cola": "1.233333333",
            "Distancia": "8.241227273",
            "velocidad": "21.16698664",
            "ley": "0.67",
            "SPI": "180.7"
        },
        {
            "fecha_hora": "2018-01-17 18:00:00",
            "chancador": "PRIM DOS",
            "viajes": "10",
            "tons": "3034",
            "tons_promedio": "303.4",
            "tiempo_cola": "0.245",
            "Distancia": "5.0087",
            "velocidad": "17.16369521",
            "ley": "0.611067897",
            "SPI": "149.2646341"
        },
        {
            "fecha_hora": "2018-01-17 19:00:00",
            "chancador": "PRIM",
            "viajes": "1",
            "tons": "298",
            "tons_promedio": "298",
            "tiempo_cola": "0.733333333",
            "Distancia": "8.44",
            "velocidad": "21.63332147",
            "ley": "0.67",
            "SPI": "180.7"
        },
        {
            "fecha_hora": "2018-01-17 19:00:00",
            "chancador": "PRIM DOS",
            "viajes": "7",
            "tons": "2086",
            "tons_promedio": "298",
            "tiempo_cola": "0.233333333",
            "Distancia": "5.192857143",
            "velocidad": "25.82338431",
            "ley": "0.618571429",
            "SPI": "153.2671429"
        },
        {
            "fecha_hora": "2018-01-17 20:00:00",
            "chancador": "PRIM DOS",
            "viajes": "3",
            "tons": "894",
            "tons_promedio": "298",
            "tiempo_cola": "3.6",
            "Distancia": "2.568666667",
            "velocidad": "56.32812183",
            "ley": "0.55",
            "SPI": "116.69"
        },
        {
            "fecha_hora": "2018-01-17 21:00:00",
            "chancador": "PRIM DOS",
            "viajes": "4",
            "tons": "1192",
            "tons_promedio": "298",
            "tiempo_cola": "0.0375",
            "Distancia": "3.336125",
            "velocidad": "17.44062443",
            "ley": "0.55",
            "SPI": "116.69"
        },
        {
            "fecha_hora": "2018-01-17 22:00:00",
            "chancador": "PRIM DOS",
            "viajes": "7",
            "tons": "2086",
            "tons_promedio": "298",
            "tiempo_cola": "0.085714286",
            "Distancia": "4.303714286",
            "velocidad": "25.30415306",
            "ley": "0.614285714",
            "SPI": "119.6514286"
        },
        {
            "fecha_hora": "2018-01-17 23:00:00",
            "chancador": "PRIM",
            "viajes": "12",
            "tons": "3684",
            "tons_promedio": "307",
            "tiempo_cola": "0.35",
            "Distancia": "8.613791667",
            "velocidad": "20.68114267",
            "ley": "0.67",
            "SPI": "180.7"
        },
        {
            "fecha_hora": "2018-01-17 23:00:00",
            "chancador": "PRIM DOS",
            "viajes": "9",
            "tons": "2709",
            "tons_promedio": "301",
            "tiempo_cola": "1.959259259",
            "Distancia": "3.016222222",
            "velocidad": "22.91338804",
            "ley": "0.666998893",
            "SPI": "122.079749"
        },
        {
            "fecha_hora": "2018-01-18 00:00:00",
            "chancador": "PRIM",
            "viajes": "16",
            "tons": "4849",
            "tons_promedio": "303.0625",
            "tiempo_cola": "5.054166667",
            "Distancia": "7.91703125",
            "velocidad": "19.71726911",
            "ley": "0.673854403",
            "SPI": "173.3637863"
        },
        {
            "fecha_hora": "2018-01-18 00:00:00",
            "chancador": "PRIM DOS",
            "viajes": "7",
            "tons": "2194",
            "tons_promedio": "313.4285714",
            "tiempo_cola": "0.369047619",
            "Distancia": "1.766428571",
            "velocidad": "15.34700914",
            "ley": "0.7",
            "SPI": "123.6"
        },
        {
            "fecha_hora": "2018-01-18 01:00:00",
            "chancador": "PRIM",
            "viajes": "15",
            "tons": "4578",
            "tons_promedio": "305.2",
            "tiempo_cola": "2.757777778",
            "Distancia": "7.2851",
            "velocidad": "18.90596886",
            "ley": "0.680117955",
            "SPI": "161.4421581"
        },
        {
            "fecha_hora": "2018-01-18 02:00:00",
            "chancador": "PRIM",
            "viajes": "10",
            "tons": "3034",
            "tons_promedio": "303.4",
            "tiempo_cola": "1.591666667",
            "Distancia": "9.8142",
            "velocidad": "19.68910808",
            "ley": "0.67",
            "SPI": "180.7"
        },
        {
            "fecha_hora": "2018-01-18 02:00:00",
            "chancador": "PRIM DOS",
            "viajes": "2",
            "tons": "596",
            "tons_promedio": "298",
            "tiempo_cola": "0.858333333",
            "Distancia": "9.95175",
            "velocidad": "22.5287219",
            "ley": "0.67",
            "SPI": "180.7"
        },
        {
            "fecha_hora": "2018-01-18 03:00:00",
            "chancador": "PRIM",
            "viajes": "6",
            "tons": "1815",
            "tons_promedio": "302.5",
            "tiempo_cola": "0.297222222",
            "Distancia": "10.05025",
            "velocidad": "21.38245752",
            "ley": "0.67",
            "SPI": "180.7"
        },
        {
            "fecha_hora": "2018-01-18 03:00:00",
            "chancador": "PRIM DOS",
            "viajes": "9",
            "tons": "2736",
            "tons_promedio": "304",
            "tiempo_cola": "0.551851852",
            "Distancia": "6.775666667",
            "velocidad": "13.15781714",
            "ley": "0.643859649",
            "SPI": "166.7563012"
        },
        {
            "fecha_hora": "2018-01-18 04:00:00",
            "chancador": "PRIM",
            "viajes": "9",
            "tons": "2736",
            "tons_promedio": "304",
            "tiempo_cola": "0.359259259",
            "Distancia": "9.397166667",
            "velocidad": "19.96316428",
            "ley": "0.67",
            "SPI": "180.7"
        },
        {
            "fecha_hora": "2018-01-18 04:00:00",
            "chancador": "PRIM DOS",
            "viajes": "6",
            "tons": "1788",
            "tons_promedio": "298",
            "tiempo_cola": "0.758333333",
            "Distancia": "8.825416667",
            "velocidad": "21.80112077",
            "ley": "0.63",
            "SPI": "159.3633333"
        },
        {
            "fecha_hora": "2018-01-18 05:00:00",
            "chancador": "PRIM",
            "viajes": "4",
            "tons": "1219",
            "tons_promedio": "304.75",
            "tiempo_cola": "0.645833333",
            "Distancia": "9.7815",
            "velocidad": "20.51465191",
            "ley": "0.67",
            "SPI": "180.7"
        },
        {
            "fecha_hora": "2018-01-18 05:00:00",
            "chancador": "PRIM DOS",
            "viajes": "13",
            "tons": "3928",
            "tons_promedio": "302.1538462",
            "tiempo_cola": "0.769230769",
            "Distancia": "7.357",
            "velocidad": "19.97143852",
            "ley": "0.642688391",
            "SPI": "166.1315326"
        },
        {
            "fecha_hora": "2018-01-18 06:00:00",
            "chancador": "PRIM",
            "viajes": "3",
            "tons": "894",
            "tons_promedio": "298",
            "tiempo_cola": "6.472222222",
            "Distancia": "10.7165",
            "velocidad": "20.08994966",
            "ley": "0.67",
            "SPI": "180.7"
        },
        {
            "fecha_hora": "2018-01-18 06:00:00",
            "chancador": "PRIM DOS",
            "viajes": "17",
            "tons": "5120",
            "tons_promedio": "301.1764706",
            "tiempo_cola": "0.597058824",
            "Distancia": "6.970323529",
            "velocidad": "17.83078917",
            "ley": "0.62809375",
            "SPI": "158.3465078"
        },
        {
            "fecha_hora": "2018-01-18 07:00:00",
            "chancador": "PRIM DOS",
            "viajes": "6",
            "tons": "1788",
            "tons_promedio": "298",
            "tiempo_cola": "2.211111111",
            "Distancia": "4.452",
            "velocidad": "19.57122214",
            "ley": "0.59",
            "SPI": "138.0266667"
        },
        {
            "fecha_hora": "2018-01-18 08:00:00",
            "chancador": "PRIM DOS",
            "viajes": "9",
            "tons": "2709",
            "tons_promedio": "301",
            "tiempo_cola": "1.674074074",
            "Distancia": "7.121833333",
            "velocidad": "44.3745",
            "ley": "0.617198228",
            "SPI": "152.5346549"
        },
        {
            "fecha_hora": "2018-01-18 09:00:00",
            "chancador": "PRIM DOS",
            "viajes": "5",
            "tons": "1490",
            "tons_promedio": "298",
            "tiempo_cola": "0",
            "Distancia": "2.5728",
            "velocidad": "20.79030303",
            "ley": "0.55",
            "SPI": "116.69"
        },
        {
            "fecha_hora": "2018-01-18 10:00:00",
            "chancador": "PRIM DOS",
            "viajes": "2",
            "tons": "596",
            "tons_promedio": "298",
            "tiempo_cola": "1.075",
            "Distancia": "4.198",
            "velocidad": "18.43586459",
            "ley": "0.625",
            "SPI": "120.145"
        },
        {
            "fecha_hora": "2018-01-18 11:00:00",
            "chancador": "PRIM DOS",
            "viajes": "12",
            "tons": "3576",
            "tons_promedio": "298",
            "tiempo_cola": "0.368055556",
            "Distancia": "1.195375",
            "velocidad": "14.65385925",
            "ley": "0.7",
            "SPI": "123.6"
        },
        {
            "fecha_hora": "2018-01-18 12:00:00",
            "chancador": "PRIM DOS",
            "viajes": "12",
            "tons": "3576",
            "tons_promedio": "298",
            "tiempo_cola": "0.422222222",
            "Distancia": "0.864",
            "velocidad": "19.39454404",
            "ley": "0.7",
            "SPI": "123.6"
        },
        {
            "fecha_hora": "2018-01-18 13:00:00",
            "chancador": "PRIM DOS",
            "viajes": "9",
            "tons": "2709",
            "tons_promedio": "301",
            "tiempo_cola": "0",
            "Distancia": "1.034277778",
            "velocidad": "15.64453782",
            "ley": "0.7",
            "SPI": "123.6"
        },
        {
            "fecha_hora": "2018-01-18 15:00:00",
            "chancador": "PRIM DOS",
            "viajes": "13",
            "tons": "4036",
            "tons_promedio": "310.4615385",
            "tiempo_cola": "0.333333333",
            "Distancia": "9.733",
            "velocidad": "21.52921659",
            "ley": "0.67",
            "SPI": "180.7"
        },
        {
            "fecha_hora": "2018-01-18 16:00:00",
            "chancador": "PRIM DOS",
            "viajes": "9",
            "tons": "2763",
            "tons_promedio": "307",
            "tiempo_cola": "0.362962963",
            "Distancia": "9.221611111",
            "velocidad": "21.0846618",
            "ley": "0.67",
            "SPI": "180.7"
        },
        {
            "fecha_hora": "2018-01-18 17:00:00",
            "chancador": "PRIM DOS",
            "viajes": "12",
            "tons": "3630",
            "tons_promedio": "302.5",
            "tiempo_cola": "2.1125",
            "Distancia": "8.395416667",
            "velocidad": "22.24087815",
            "ley": "0.67",
            "SPI": "180.7"
        },
        {
            "fecha_hora": "2018-01-18 18:00:00",
            "chancador": "PRIM DOS",
            "viajes": "11",
            "tons": "3413",
            "tons_promedio": "310.2727273",
            "tiempo_cola": "0.351515152",
            "Distancia": "8.698772727",
            "velocidad": "20.36725596",
            "ley": "0.67",
            "SPI": "180.7"
        },
        {
            "fecha_hora": "2018-01-18 19:00:00",
            "chancador": "PRIM DOS",
            "viajes": "1",
            "tons": "298",
            "tons_promedio": "298",
            "tiempo_cola": "1.833333333",
            "Distancia": "8.4545",
            "velocidad": "25.85913339",
            "ley": "0.67",
            "SPI": "180.7"
        },
        {
            "fecha_hora": "2018-01-18 22:00:00",
            "chancador": "PRIM DOS",
            "viajes": "1",
            "tons": "298",
            "tons_promedio": "298",
            "tiempo_cola": "0",
            "Distancia": "4.7345",
            "velocidad": "13.85707317",
            "ley": "0.46",
            "SPI": "67.5"
        },
        {
            "fecha_hora": "2018-01-18 23:00:00",
            "chancador": "PRIM",
            "viajes": "2",
            "tons": "623",
            "tons_promedio": "311.5",
            "tiempo_cola": "0",
            "Distancia": "5.5315",
            "velocidad": "13.8552096",
            "ley": "0.46",
            "SPI": "67.5"
        },
        {
            "fecha_hora": "2018-01-18 23:00:00",
            "chancador": "PRIM DOS",
            "viajes": "17",
            "tons": "5228",
            "tons_promedio": "307.5294118",
            "tiempo_cola": "2.256862745",
            "Distancia": "6.734382353",
            "velocidad": "16.79581882",
            "ley": "0.498393267",
            "SPI": "106.6020628"
        },
        {
            "fecha_hora": "2018-01-19 00:00:00",
            "chancador": "PRIM",
            "viajes": "4",
            "tons": "1219",
            "tons_promedio": "304.75",
            "tiempo_cola": "5.8125",
            "Distancia": "10.34475",
            "velocidad": "17.15784381",
            "ley": "0.558219852",
            "SPI": "167.5331344"
        },
        {
            "fecha_hora": "2018-01-19 00:00:00",
            "chancador": "PRIM DOS",
            "viajes": "14",
            "tons": "4280",
            "tons_promedio": "305.7142857",
            "tiempo_cola": "3.75",
            "Distancia": "7.168142857",
            "velocidad": "19.43432583",
            "ley": "0.506897196",
            "SPI": "115.262987"
        },
        {
            "fecha_hora": "2018-01-19 01:00:00",
            "chancador": "PRIM",
            "viajes": "7",
            "tons": "2140",
            "tons_promedio": "305.7142857",
            "tiempo_cola": "2.238095238",
            "Distancia": "8.675071429",
            "velocidad": "20.34923206",
            "ley": "0.552154206",
            "SPI": "161.3555069"
        },
        {
            "fecha_hora": "2018-01-19 01:00:00",
            "chancador": "PRIM DOS",
            "viajes": "11",
            "tons": "3359",
            "tons_promedio": "305.3636364",
            "tiempo_cola": "6.101515152",
            "Distancia": "8.238954545",
            "velocidad": "20.66588124",
            "ley": "0.531289074",
            "SPI": "140.1051746"
        },
        {
            "fecha_hora": "2018-01-19 02:00:00",
            "chancador": "PRIM DOS",
            "viajes": "11",
            "tons": "3332",
            "tons_promedio": "302.9090909",
            "tiempo_cola": "2.139393939",
            "Distancia": "9.430045455",
            "velocidad": "18.46925169",
            "ley": "0.59",
            "SPI": "199.89999"
        },
        {
            "fecha_hora": "2018-01-19 03:00:00",
            "chancador": "PRIM DOS",
            "viajes": "13",
            "tons": "3928",
            "tons_promedio": "302.1538462",
            "tiempo_cola": "2.871794872",
            "Distancia": "9.216346154",
            "velocidad": "21.90022848",
            "ley": "0.67",
            "SPI": "180.7"
        },
        {
            "fecha_hora": "2018-01-19 04:00:00",
            "chancador": "PRIM",
            "viajes": "1",
            "tons": "298",
            "tons_promedio": "298",
            "tiempo_cola": "12.51666667",
            "Distancia": "7.69",
            "velocidad": "23.1665272",
            "ley": "0.59",
            "SPI": "199.89999"
        },
        {
            "fecha_hora": "2018-01-19 04:00:00",
            "chancador": "PRIM DOS",
            "viajes": "16",
            "tons": "4822",
            "tons_promedio": "301.375",
            "tiempo_cola": "5.464583333",
            "Distancia": "9.05409375",
            "velocidad": "18.87225157",
            "ley": "0.647133969",
            "SPI": "187.8749865"
        },
        {
            "fecha_hora": "2018-01-19 05:00:00",
            "chancador": "PRIM",
            "viajes": "8",
            "tons": "2465",
            "tons_promedio": "308.125",
            "tiempo_cola": "6.316666667",
            "Distancia": "8.169",
            "velocidad": "18.81159397",
            "ley": "0.741314402",
            "SPI": "167.8061751"
        },
        {
            "fecha_hora": "2018-01-19 05:00:00",
            "chancador": "PRIM DOS",
            "viajes": "16",
            "tons": "4822",
            "tons_promedio": "301.375",
            "tiempo_cola": "6.357291667",
            "Distancia": "8.18175",
            "velocidad": "17.92169151",
            "ley": "0.669377852",
            "SPI": "147.4739999"
        },
        {
            "fecha_hora": "2018-01-19 06:00:00",
            "chancador": "PRIM",
            "viajes": "14",
            "tons": "4253",
            "tons_promedio": "303.7857143",
            "tiempo_cola": "7.280952381",
            "Distancia": "9.761714286",
            "velocidad": "19.57781138",
            "ley": "0.71",
            "SPI": "188.3"
        },
        {
            "fecha_hora": "2018-01-19 06:00:00",
            "chancador": "PRIM DOS",
            "viajes": "9",
            "tons": "2709",
            "tons_promedio": "301",
            "tiempo_cola": "7.268518519",
            "Distancia": "6.021888889",
            "velocidad": "18.8867141",
            "ley": "0.46",
            "SPI": "67.5"
        },
        {
            "fecha_hora": "2018-01-19 07:00:00",
            "chancador": "PRIM",
            "viajes": "2",
            "tons": "623",
            "tons_promedio": "311.5",
            "tiempo_cola": "4.441666667",
            "Distancia": "8.69675",
            "velocidad": "29.4112729",
            "ley": "0.71",
            "SPI": "188.3"
        },
        {
            "fecha_hora": "2018-01-19 07:00:00",
            "chancador": "PRIM DOS",
            "viajes": "1",
            "tons": "298",
            "tons_promedio": "298",
            "tiempo_cola": "0",
            "Distancia": "8.1885",
            "velocidad": "22.35767918",
            "ley": "0.71",
            "SPI": "188.3"
        },
        {
            "fecha_hora": "2018-01-19 08:00:00",
            "chancador": "PRIM",
            "viajes": "11",
            "tons": "3332",
            "tons_promedio": "302.9090909",
            "tiempo_cola": "1.715151515",
            "Distancia": "9.844181818",
            "velocidad": "31.45182137",
            "ley": "0.611542617",
            "SPI": "184.8523346"
        },
        {
            "fecha_hora": "2018-01-19 08:00:00",
            "chancador": "PRIM DOS",
            "viajes": "14",
            "tons": "4307",
            "tons_promedio": "307.6428571",
            "tiempo_cola": "1.820238095",
            "Distancia": "7.0035",
            "velocidad": "30.94112903",
            "ley": "0.496101695",
            "SPI": "95.00954116"
        },
        {
            "fecha_hora": "2018-01-19 09:00:00",
            "chancador": "PRIM",
            "viajes": "5",
            "tons": "1571",
            "tons_promedio": "314.2",
            "tiempo_cola": "1.45",
            "Distancia": "9.14",
            "velocidad": "12.91822072",
            "ley": "0.59",
            "SPI": "199.89999"
        },
        {
            "fecha_hora": "2018-01-19 09:00:00",
            "chancador": "PRIM DOS",
            "viajes": "13",
            "tons": "4036",
            "tons_promedio": "310.4615385",
            "tiempo_cola": "4.35",
            "Distancia": "8.771346154",
            "velocidad": "15.84968822",
            "ley": "0.558595144",
            "SPI": "167.9153542"
        },
        {
            "fecha_hora": "2018-01-19 10:00:00",
            "chancador": "PRIM",
            "viajes": "7",
            "tons": "2221",
            "tons_promedio": "317.2857143",
            "tiempo_cola": "1.407142857",
            "Distancia": "9.088071429",
            "velocidad": "23.08663306",
            "ley": "0.59",
            "SPI": "199.89999"
        },
        {
            "fecha_hora": "2018-01-19 10:00:00",
            "chancador": "PRIM DOS",
            "viajes": "6",
            "tons": "1815",
            "tons_promedio": "302.5",
            "tiempo_cola": "3.894444444",
            "Distancia": "8.024083333",
            "velocidad": "21.80402566",
            "ley": "0.568655647",
            "SPI": "178.1615894"
        },
        {
            "fecha_hora": "2018-01-19 11:00:00",
            "chancador": "PRIM",
            "viajes": "11",
            "tons": "3386",
            "tons_promedio": "307.8181818",
            "tiempo_cola": "2.183333333",
            "Distancia": "7.897681818",
            "velocidad": "23.66167581",
            "ley": "0.578558771",
            "SPI": "188.2475396"
        },
        {
            "fecha_hora": "2018-01-19 11:00:00",
            "chancador": "PRIM DOS",
            "viajes": "20",
            "tons": "6014",
            "tons_promedio": "300.7",
            "tiempo_cola": "3.913333333",
            "Distancia": "6.8221",
            "velocidad": "19.34166289",
            "ley": "0.511533089",
            "SPI": "119.9844656"
        },
        {
            "fecha_hora": "2018-01-19 12:00:00",
            "chancador": "PRIM",
            "viajes": "9",
            "tons": "2763",
            "tons_promedio": "307",
            "tiempo_cola": "3.561111111",
            "Distancia": "7.859722222",
            "velocidad": "20.3114656",
            "ley": "0.532645675",
            "SPI": "141.4868203"
        },
        {
            "fecha_hora": "2018-01-19 12:00:00",
            "chancador": "PRIM DOS",
            "viajes": "11",
            "tons": "3332",
            "tons_promedio": "302.9090909",
            "tiempo_cola": "5.313636364",
            "Distancia": "6.881409091",
            "velocidad": "18.82842534",
            "ley": "0.494879952",
            "SPI": "103.0238869"
        },
        {
            "fecha_hora": "2018-01-19 13:00:00",
            "chancador": "PRIM DOS",
            "viajes": "13",
            "tons": "3928",
            "tons_promedio": "302.1538462",
            "tiempo_cola": "1.187179487",
            "Distancia": "8.644961538",
            "velocidad": "21.28942328",
            "ley": "0.70496945",
            "SPI": "154.8469272"
        },
        {
            "fecha_hora": "2018-01-19 14:00:00",
            "chancador": "PRIM",
            "viajes": "2",
            "tons": "596",
            "tons_promedio": "298",
            "tiempo_cola": "3.825",
            "Distancia": "9.2525",
            "velocidad": "20.39118457",
            "ley": "0.78",
            "SPI": "181.60001"
        },
        {
            "fecha_hora": "2018-01-19 14:00:00",
            "chancador": "PRIM DOS",
            "viajes": "14",
            "tons": "4280",
            "tons_promedio": "305.7142857",
            "tiempo_cola": "1.451190476",
            "Distancia": "8.223928571",
            "velocidad": "20.10311378",
            "ley": "0.78",
            "SPI": "181.60001"
        },
        {
            "fecha_hora": "2018-01-19 15:00:00",
            "chancador": "PRIM",
            "viajes": "5",
            "tons": "1490",
            "tons_promedio": "298",
            "tiempo_cola": "0.64",
            "Distancia": "8.6407",
            "velocidad": "20.65917513",
            "ley": "0.78",
            "SPI": "181.60001"
        },
        {
            "fecha_hora": "2018-01-19 15:00:00",
            "chancador": "PRIM DOS",
            "viajes": "9",
            "tons": "2790",
            "tons_promedio": "310",
            "tiempo_cola": "1.305555556",
            "Distancia": "9.264166667",
            "velocidad": "19.73107642",
            "ley": "0.78",
            "SPI": "181.60001"
        },
        {
            "fecha_hora": "2018-01-19 16:00:00",
            "chancador": "PRIM",
            "viajes": "8",
            "tons": "2411",
            "tons_promedio": "301.375",
            "tiempo_cola": "1.5875",
            "Distancia": "9.8140625",
            "velocidad": "24.29682799",
            "ley": "0.78",
            "SPI": "181.60001"
        },
        {
            "fecha_hora": "2018-01-19 16:00:00",
            "chancador": "PRIM DOS",
            "viajes": "5",
            "tons": "1571",
            "tons_promedio": "314.2",
            "tiempo_cola": "1.453333333",
            "Distancia": "9.2127",
            "velocidad": "20.88126928",
            "ley": "0.78",
            "SPI": "181.60001"
        },
        {
            "fecha_hora": "2018-01-19 17:00:00",
            "chancador": "PRIM",
            "viajes": "16",
            "tons": "4822",
            "tons_promedio": "301.375",
            "tiempo_cola": "1.713541667",
            "Distancia": "5.08034375",
            "velocidad": "20.20003451",
            "ley": "0.718880133",
            "SPI": "145.2344921"
        },
        {
            "fecha_hora": "2018-01-19 17:00:00",
            "chancador": "PRIM DOS",
            "viajes": "15",
            "tons": "4632",
            "tons_promedio": "308.8",
            "tiempo_cola": "3.352222222",
            "Distancia": "7.875566667",
            "velocidad": "18.02838551",
            "ley": "0.654611399",
            "SPI": "136.891133"
        },
        {
            "fecha_hora": "2018-01-19 18:00:00",
            "chancador": "PRIM",
            "viajes": "11",
            "tons": "3305",
            "tons_promedio": "300.4545455",
            "tiempo_cola": "1.539393939",
            "Distancia": "4.158272727",
            "velocidad": "16.51216846",
            "ley": "0.686226929",
            "SPI": "134.8757677"
        },
        {
            "fecha_hora": "2018-01-19 18:00:00",
            "chancador": "PRIM DOS",
            "viajes": "17",
            "tons": "5228",
            "tons_promedio": "307.5294118",
            "tiempo_cola": "3.388235294",
            "Distancia": "7.431382353",
            "velocidad": "19.02055958",
            "ley": "0.609227238",
            "SPI": "120.7088417"
        },
        {
            "fecha_hora": "2018-01-19 19:00:00",
            "chancador": "PRIM",
            "viajes": "3",
            "tons": "894",
            "tons_promedio": "298",
            "tiempo_cola": "0",
            "Distancia": "8.261833333",
            "velocidad": "22.04516368",
            "ley": "0.78",
            "SPI": "181.60001"
        },
        {
            "fecha_hora": "2018-01-19 19:00:00",
            "chancador": "PRIM DOS",
            "viajes": "3",
            "tons": "894",
            "tons_promedio": "298",
            "tiempo_cola": "3.194444444",
            "Distancia": "5.143",
            "velocidad": "20.66383929",
            "ley": "0.46",
            "SPI": "67.5"
        },
        {
            "fecha_hora": "2018-01-19 20:00:00",
            "chancador": "PRIM",
            "viajes": "13",
            "tons": "3874",
            "tons_promedio": "298",
            "tiempo_cola": "0.676923077",
            "Distancia": "8.830769231",
            "velocidad": "36.20499343",
            "ley": "0.78",
            "SPI": "181.60001"
        },
        {
            "fecha_hora": "2018-01-19 20:00:00",
            "chancador": "PRIM DOS",
            "viajes": "15",
            "tons": "4578",
            "tons_promedio": "305.2",
            "tiempo_cola": "4.508888889",
            "Distancia": "6.8247",
            "velocidad": "32.11063867",
            "ley": "0.528152031",
            "SPI": "91.80046085"
        },
        {
            "fecha_hora": "2018-01-19 21:00:00",
            "chancador": "PRIM",
            "viajes": "14",
            "tons": "4199",
            "tons_promedio": "299.9285714",
            "tiempo_cola": "1.919047619",
            "Distancia": "8.880142857",
            "velocidad": "20.23232223",
            "ley": "0.78",
            "SPI": "181.60001"
        },
        {
            "fecha_hora": "2018-01-19 21:00:00",
            "chancador": "PRIM DOS",
            "viajes": "15",
            "tons": "4659",
            "tons_promedio": "310.6",
            "tiempo_cola": "1.488888889",
            "Distancia": "5.789933333",
            "velocidad": "17.24953243",
            "ley": "0.502790298",
            "SPI": "82.75741709"
        },
        {
            "fecha_hora": "2018-01-19 22:00:00",
            "chancador": "PRIM",
            "viajes": "11",
            "tons": "3278",
            "tons_promedio": "298",
            "tiempo_cola": "4.421212121",
            "Distancia": "8.829727273",
            "velocidad": "17.85240478",
            "ley": "0.73",
            "SPI": "181.1909145"
        },
        {
            "fecha_hora": "2018-01-19 22:00:00",
            "chancador": "PRIM DOS",
            "viajes": "20",
            "tons": "6014",
            "tons_promedio": "300.7",
            "tiempo_cola": "2.361666667",
            "Distancia": "6.763775",
            "velocidad": "18.14594504",
            "ley": "0.540176255",
            "SPI": "107.8252749"
        },
        {
            "fecha_hora": "2018-01-19 23:00:00",
            "chancador": "PRIM",
            "viajes": "5",
            "tons": "1517",
            "tons_promedio": "303.4",
            "tiempo_cola": "1.246666667",
            "Distancia": "8.1829",
            "velocidad": "19.7707651",
            "ley": "0.583757416",
            "SPI": "134.2111404"
        },
        {
            "fecha_hora": "2018-01-19 23:00:00",
            "chancador": "PRIM DOS",
            "viajes": "4",
            "tons": "1246",
            "tons_promedio": "311.5",
            "tiempo_cola": "9.875",
            "Distancia": "5.7985",
            "velocidad": "20.04041762",
            "ley": "0.514775281",
            "SPI": "97.02648475"
        }
]